{"cameraMode":{"drawMode":0,"name":"Shaded","section":"Shading Mode"},"sceneLighting":true,"audioPlay":false,"sceneViewState":{"showFog":true,"showMaterialUpdate":false,"showSkybox":true,"showFlares":true,"showImageEffects":true,"showParticleSystems":true},"in2DMode":false,"pivot":{"x":-24.151254653930665,"y":1.3915072679519654,"z":-53.25035095214844},"rotation":{"x":0.13876566290855409,"y":-0.7148320078849793,"z":0.1482473760843277,"w":0.6691651940345764},"size":17.9671688079834,"orthographic":false}